classendar/decorator.py
classendar-1.0.1.dist-info/METADATA
classendar-1.0.1.dist-info/WHEEL
classendar-1.0.1.dist-info/top_level.txt
classendar-1.0.1.dist-info/RECORD
