Metadata-Version: 2.4
Name: classendar
Version: 1.0.1
Summary: Versioned classes based on dates
Author-email: Jack <jackxxu@gmail.com>
Requires-Python: >=3.8
